pytgen/__init__.py
pytgen-0.0.2.dist-info/METADATA
pytgen-0.0.2.dist-info/WHEEL
pytgen-0.0.2.dist-info/top_level.txt
pytgen-0.0.2.dist-info/RECORD
